mini_os_scheduler/__init__.py
mini_os_scheduler/algorithms.py
mini_os_scheduler/main.py
mini_os_scheduler/models.py
mini_os_scheduler/simulator.py
mini_os_scheduler/web/__init__.py
mini_os_scheduler/web/app.py
mini_os_scheduler/web/templates/index.html
mini_os_scheduler-0.1.0.dist-info/licenses/LICENSE
mini_os_scheduler-0.1.0.dist-info/METADATA
mini_os_scheduler-0.1.0.dist-info/WHEEL
mini_os_scheduler-0.1.0.dist-info/entry_points.txt
mini_os_scheduler-0.1.0.dist-info/top_level.txt
mini_os_scheduler-0.1.0.dist-info/RECORD
