Metadata-Version: 2.4
Name: mini-os-scheduler
Version: 0.1.0
Summary: A comprehensive CPU scheduling simulator implementing FCFS, SJF, Priority, and Round Robin algorithms
Author-email: Binod Karki <karkibinod367@gmail.com>
Maintainer-email: Binod Karki <karkibinod367@gmail.com>
License: MIT
Project-URL: Homepage, https://github.com/Karkibinod/mini-os-scheduler
Project-URL: Documentation, https://github.com/Karkibinod/mini-os-scheduler#readme
Project-URL: Repository, https://github.com/Karkibinod/mini-os-scheduler
Project-URL: Issues, https://github.com/Karkibinod/mini-os-scheduler/issues
Project-URL: Changelog, https://github.com/Karkibinod/mini-os-scheduler/blob/main/CHANGELOG.md
Keywords: cpu,scheduler,scheduling,operating-systems,fcfs,sjf,round-robin,priority-scheduling,simulator,os,process-scheduling
Classifier: Development Status :: 4 - Beta
Classifier: Intended Audience :: Education
Classifier: Intended Audience :: Developers
Classifier: Topic :: Education
Classifier: Topic :: System :: Operating System
Classifier: Topic :: Software Development :: Libraries :: Python Modules
Classifier: License :: OSI Approved :: MIT License
Classifier: Programming Language :: Python :: 3
Classifier: Programming Language :: Python :: 3.7
Classifier: Programming Language :: Python :: 3.8
Classifier: Programming Language :: Python :: 3.9
Classifier: Programming Language :: Python :: 3.10
Classifier: Programming Language :: Python :: 3.11
Classifier: Programming Language :: Python :: 3.12
Classifier: Programming Language :: Python :: 3.13
Classifier: Operating System :: OS Independent
Requires-Python: >=3.7
License-File: LICENSE
Provides-Extra: web
Requires-Dist: flask>=2.0.0; extra == "web"
Provides-Extra: dev
Requires-Dist: pytest>=7.0.0; extra == "dev"
Requires-Dist: pytest-cov>=4.0.0; extra == "dev"
Requires-Dist: black>=23.0.0; extra == "dev"
Requires-Dist: flake8>=6.0.0; extra == "dev"
Dynamic: license-file
